MANIFEST.in
README.md
setup.py
loggus/__init__.py
loggus/fields.py
loggus/formatter.py
loggus/frame.py
loggus/hooks.py
loggus/level.py
loggus/utils.py
loggus.egg-info/PKG-INFO
loggus.egg-info/SOURCES.txt
loggus.egg-info/dependency_links.txt
loggus.egg-info/requires.txt
loggus.egg-info/top_level.txt