Metadata-Version: 1.1
Name: loggus
Version: 0.1.2
Summary: 基于 python 的结构化日志库。利用 python 动态语言的特性，实现了一些独特功能。
Home-page: https://github.com/czasg/loggus
Author: czasg
Author-email: 972542644@qq.com
License: UNKNOWN
Platform: UNKNOWN
Classifier: Programming Language :: Python :: 3.6
Classifier: Programming Language :: Python :: 3.7
